{
  "id": "fix-trellis-staging-scope",
  "name": "fix-trellis-staging-scope",
  "title": "fix: .trellis staging 范围失控类 bug（#303）",
  "description": "",
  "status": "in_progress",
  "dev_type": null,
  "scope": null,
  "package": null,
  "priority": "P2",
  "creator": "taosu",
  "assignee": "taosu",
  "createdAt": "2026-06-18",
  "completedAt": null,
  "branch": null,
  "base_branch": "main",
  "worktree_path": null,
  "commit": null,
  "pr_url": null,
  "subtasks": [],
  "children": [],
  "parent": null,
  "relatedFiles": [],
  "notes": "",
  "meta": {}
}